{
    "keyboard_name": "roe_wildpad",
    "manufacturer": "roe",
    "maintainer": "roe",
    "usb": {
        "vid": "0xFEED",
        "pid": "0x6969",
        "device_version": "1.0.0"
    },
    "processor": "RP2040",
    "bootloader": "rp2040",
    "features": {
        "bootmagic": true,
        "extrakey": true,
        "encoder": true,
        "oled": true
    },
    "matrix_pins": {
        "cols": ["GP26", "GP27", "GP28"],
        "rows": ["GP29", "GP3"]
    },
    "diode_direction": "COL2ROW",
    "encoder": {
        "rotary": [
            {
                "pin_a": "GP11",
                "pin_b": "GP10"
            }
        ]
    },
    "layouts": {
        "LAYOUT": {
            "layout": [
                { "matrix": [0, 0], "x": 0, "y": 0, "label": "R0C0" },
                { "matrix": [0, 1], "x": 1, "y": 0, "label": "R0C1" },
                { "matrix": [0, 2], "x": 2, "y": 0, "label": "ENC_BTN" },
                { "matrix": [1, 0], "x": 0, "y": 1, "label": "R1C0" },
                { "matrix": [1, 1], "x": 1, "y": 1, "label": "R1C1" },
                { "matrix": [1, 2], "x": 2, "y": 1, "label": "LAYER" }
            ]
        }
    }
}
